quantum_env/__init__.py
quantum_env/quantum_core.py
scene_env/__init__.py
scene_env/fluid_sim.py
scene_env/game_env.py
scene_env/human_env.py
scene_env/scene.py
sim_env/AI_Director.py
sim_env/Advanced_Research_features.py
sim_env/Astrophysics_&_Cosmic_simulations.py
sim_env/Audio_Integration.py
sim_env/Biological_Cellular_Automata.py
sim_env/Example_Usage.py
sim_env/Export_Options.py
sim_env/Gadget_&_System_creator.py
sim_env/Interactive_input_System.py
sim_env/NeRF_Integration.py
sim_env/Physics_simulation_module.py
sim_env/Quantum_Physics_simulations.py
sim_env/Rendering_engine.py
sim_env/User_Interface_&_Neural_Integration.py
sim_env/__init__.py
sim_env/enterprise_distributed_system.py
sim_env/example_simulations.py
sim_env/fluid_dynamics.py
sim_env/holographic_neural_Rendering.py
sim_env/integration.py
sim_env/main.py
sim_env/ml_enhacements.py
sim_env/ml_pipeline.py
sim_env/multiscale_physics.py
sim_env/natural_Language_Parser.py
sim_env/network_effects.py
sim_env/neural_Physics.py
sim_env/particle_system.py
sim_env/problem_solver.py
sim_env/quantum_computing_Hybrid.py
sim_env/ray_&_Path_Tracing.py
sim_env/realtime_gui.py
sim_env/scene.py
sim_env/security.py
sim_env/security_&_Encryption.py
sim_env/ultimate_Virtual_Laboratory.py
sim_env/web_Interface.py
tests/__init__.py
tests/conftest.py
tests/test_basics.py
tests/test_config.py
tests/test_ml_pipeline.py
tests/test_quantum_env.py
tests/test_scene_env.py
tests/test_simulation_helpers.py
tests/test_test_utils.py
tests/test_video_tooks.py
tests/integration/__init__.py
tests/integration/test_combined_pipeline.py
tests/integration/test_quantum_pipeline.py
tests/integration/test_scene_pipeline.py
tests/test_scene_env/__init__.py
tests/test_scene_env/test_fluid_sim.py
tests/test_scene_env/test_game_env.py
tests/test_scene_env/test_human_env.py
tests/test_scene_env/test_scene.py
tests/test_utils/__init__.py
tests/test_utils/assertions.py
tests/test_utils/mocks.py
utils/__init__.py
utils/config.py
frextech_simulation-0.1.0.dist-info/METADATA
frextech_simulation-0.1.0.dist-info/WHEEL
frextech_simulation-0.1.0.dist-info/top_level.txt
frextech_simulation-0.1.0.dist-info/RECORD
