Metadata-Version: 2.4
Name: frextech_simulation
Version: 0.1.0
Summary: FrexTech's modular simulation engine
Author: Nkuranga
License: MIT
Dynamic: author
Dynamic: summary
